enilm/__init__.py
enilm/_modidx.py
enilm/activations.py
enilm/active.py
enilm/appliances.py
enilm/checkers.py
enilm/clip.py
enilm/config.py
enilm/config_file.py
enilm/constants.py
enilm/context.py
enilm/convert.py
enilm/core.py
enilm/duplicate.py
enilm/feather.py
enilm/lite.py
enilm/load_kwargs.py
enilm/logger.py
enilm/metrics.py
enilm/paths.py
enilm/seed.py
enilm/ser.py
enilm/windowing.py
enilm/cache/__base__.py
enilm/cache/__init__.py
enilm/cache/dictc.py
enilm/cache/nparr.py
enilm/cache/pdser.py
enilm/data/__init__.py
enilm/data/fake.py
enilm/datasets/__init__.py
enilm/datasets/__main__.py
enilm/datasets/ac_types.py
enilm/datasets/availability.py
enilm/datasets/coords.py
enilm/datasets/loaders.py
enilm/dicthelpers/__init__.py
enilm/dicthelpers/hashable.py
enilm/dicthelpers/nested.py
enilm/dicthelpers/save_load.py
enilm/distance/__init__.py
enilm/distance/cluster.py
enilm/distance/dist.py
enilm/dt/__init__.py
enilm/dt/common.py
enilm/dt/nilmtktf.py
enilm/dt/sun.py
enilm/dt/workday.py
enilm/esp/__init__.py
enilm/esp/http.py
enilm/esp/ser.py
enilm/esp/demo/__init__.py
enilm/esp/demo/common.py
enilm/esp/demo/ser_interactive.py
enilm/esp/demo/mtl/__init__.py
enilm/esp/demo/mtl/http.py
enilm/esp/demo/mtl/ser.py
enilm/esp/http/__init__.py
enilm/esp/http/__main__.py
enilm/esp/http/interface.py
enilm/esp/http/pred.py
enilm/etypes/__init__.py
enilm/etypes/__main__.py
enilm/etypes/arr.py
enilm/etypes/esp.py
enilm/etypes/measures.py
enilm/etypes/ser.py
enilm/etypes/xy.py
enilm/gpu/__init__.py
enilm/gpu/tf.py
enilm/gpu/torch.py
enilm/ipython/__init__.py
enilm/ipython/load_train.py
enilm/ipython/magic.py
enilm/ipython/path.py
enilm/ipython/section.py
enilm/keras/__init__.py
enilm/keras/metrics.py
enilm/losses/__init__.py
enilm/losses/f1.py
enilm/losses/mae.py
enilm/losses/sae.py
enilm/losses/splitted.py
enilm/losses/utils.py
enilm/measures/__init__.py
enilm/measures/measures.py
enilm/measures/total.py
enilm/models/__init__.py
enilm/models/dae.py
enilm/models/fcn.py
enilm-0.0.2.dist-info/LICENSE
enilm-0.0.2.dist-info/METADATA
enilm-0.0.2.dist-info/WHEEL
enilm-0.0.2.dist-info/entry_points.txt
enilm-0.0.2.dist-info/top_level.txt
enilm-0.0.2.dist-info/RECORD
